{
    "type": "FeatureCollection",
    "totalFeatures": 3,
    "features": [{
        "type": "Feature",
        "geometry": {
            "type": "LineString",
            "coordinates": [
                [18.003566, 53.123818],
                [18.003631, 53.123964],
                [18.004695, 53.123798],
                [18.00668, 53.123513],
                [18.007319, 53.123261],
                [18.007289, 53.123208],
                [18.007265, 53.122765],
                [18.007925, 53.122561],
                [18.008021, 53.122602],
                [18.009609, 53.122371],
                [18.009491, 53.122186],
                [18.009472, 53.122105],
                [18.009497, 53.121941],
                [18.009312, 53.121926]
            ]
        },
        "properties": {}
    }, {
        "type": "Feature",
        "geometry": {
            "type": "MultiPolygon",
            "coordinates": [
                [
                    [
                        [18.004532, 53.123562],
                        [18.004615, 53.123777],
                        [18.003537, 53.123914],
                        [18.003462, 53.123885],
                        [18.003368, 53.123692],
                        [18.003408, 53.123686],
                        [18.003376, 53.12362],
                        [18.003317, 53.123607],
                        [18.003177, 53.123328],
                        [18.003191, 53.123261],
                        [18.003786, 53.12313],
                        [18.003826, 53.123211],
                        [18.003376, 53.123311],
                        [18.003491, 53.12355],
                        [18.003596, 53.123533],
                        [18.003617, 53.123586],
                        [18.003585, 53.123596],
                        [18.003606, 53.123644],
                        [18.003639, 53.123634],
                        [18.00366, 53.123679],
                        [18.003615, 53.123689],
                        [18.003631, 53.123729],
                        [18.003708, 53.123753],
                        [18.004398, 53.12365],
                        [18.004379, 53.123584],
                        [18.004532, 53.123562]
                    ]
                ]
            ]
        },
        "properties": {}
    }, {
        "type": "Feature",
        "geometry": {
            "type": "MultiPolygon",
            "coordinates": [
                [
                    [
                        [18.008649, 53.121928],
                        [18.008676, 53.121761],
                        [18.009405, 53.121806],
                        [18.009379, 53.121973],
                        [18.008649, 53.121928]
                    ]
                ]
            ]
        },
        "properties": {}
    }]
}
